odoo/addons/stock_product_security/README.rst
odoo/addons/stock_product_security/__init__.py
odoo/addons/stock_product_security/__manifest__.py
odoo/addons/stock_product_security/i18n/ca.po
odoo/addons/stock_product_security/i18n/es.po
odoo/addons/stock_product_security/i18n/it.po
odoo/addons/stock_product_security/i18n/stock_product_security.pot
odoo/addons/stock_product_security/readme/CONFIGURE.md
odoo/addons/stock_product_security/readme/CONTRIBUTORS.md
odoo/addons/stock_product_security/readme/DESCRIPTION.md
odoo/addons/stock_product_security/security/ir.model.access.csv
odoo/addons/stock_product_security/security/stock_security.xml
odoo/addons/stock_product_security/static/description/icon.png
odoo/addons/stock_product_security/static/description/icon.svg
odoo/addons/stock_product_security/static/description/index.html
odoo_addon_stock_product_security-17.0.1.0.0.4.dist-info/METADATA
odoo_addon_stock_product_security-17.0.1.0.0.4.dist-info/WHEEL
odoo_addon_stock_product_security-17.0.1.0.0.4.dist-info/top_level.txt
odoo_addon_stock_product_security-17.0.1.0.0.4.dist-info/RECORD
